VerifyOwner/VerifyOwnerF.cpython-39-darwin.so
VerifyOwner/__init__.py
VerifyOwner/__main__.py
VerifyOwner/_wrapper.py
VerifyOwner/version.py
VerifyOwner-1.0.1.dist-info/LICENSE
VerifyOwner-1.0.1.dist-info/METADATA
VerifyOwner-1.0.1.dist-info/WHEEL
VerifyOwner-1.0.1.dist-info/top_level.txt
VerifyOwner-1.0.1.dist-info/RECORD
