Metadata-Version: 2.1
Name: VerifyOwner
Version: 1.0.1
Summary: Python Touch ID module
Home-page: https://github.com/Aliebc/VerifyOwner
Author: AliebcX
Author-email: AliebcX <aliebcx@outlook.com>
License: MIT LICENSE
Project-URL: Homepage, https://github.com/Aliebc/VerifyOwner
Project-URL: Bug Tracker, https://github.com/Aliebc/VerifyOwner
Platform: Darwin
Classifier: Programming Language :: Python :: 3
Classifier: License :: OSI Approved :: MIT License
Classifier: Operating System :: MacOS
Requires-Python: >=3.4
License-File: LICENSE
